pythainav/__init__.py
pythainav/api.py
pythainav/fund.py
pythainav/nav.py
pythainav/sources.py
pythainav/utils/_optional.py
pythainav/utils/date.py
pythainav-0.2.1.dist-info/LICENSE.md
pythainav-0.2.1.dist-info/WHEEL
pythainav-0.2.1.dist-info/METADATA
pythainav-0.2.1.dist-info/RECORD
