Metadata-Version: 2.1
Name: pythainav
Version: 0.2.1
Summary: a Python interface to pull thai mutual fund NAV
Home-page: https://github.com/CircleOnCircles/pythainav
License: MIT
Author: Nutchanon Ninyawee
Author-email: me@nutchanon.org
Maintainer: Nutchanon Ninyawee
Maintainer-email: me@nutchanon.org
Requires-Python: >=3.7,<4.0
Classifier: License :: OSI Approved :: MIT License
Classifier: Programming Language :: Python :: 3
Classifier: Programming Language :: Python :: 3.7
Classifier: Programming Language :: Python :: 3.8
Classifier: Programming Language :: Python :: 3.9
Requires-Dist: dataclasses (>=0.7.0,<0.8.0); python_version == "3.6"
Requires-Dist: dateparser (>=1.0.0,<2.0.0)
Requires-Dist: furl (>=2.1,<3.0)
Requires-Dist: fuzzywuzzy[speedup] (>=0.17,<0.19)
Requires-Dist: importlib-metadata (>=4.8.1,<5.0.0)
Requires-Dist: requests (>=2.22,<3.0)
Requires-Dist: typing-extensions (>=3.10.0,<4.0.0)
Project-URL: Repository, https://github.com/CircleOnCircles/pythainav
